fast_alchemy/__init__.py
fast_alchemy/export.py
fast_alchemy/helpers.py
fast_alchemy-0.1.7.dist-info/AUTHORS
fast_alchemy-0.1.7.dist-info/LICENSE
fast_alchemy-0.1.7.dist-info/METADATA
fast_alchemy-0.1.7.dist-info/WHEEL
fast_alchemy-0.1.7.dist-info/pbr.json
fast_alchemy-0.1.7.dist-info/top_level.txt
fast_alchemy-0.1.7.dist-info/RECORD
