Metadata-Version: 2.1
Name: fast-alchemy
Version: 0.1.7
Summary: Testing/Prototyping tool for SQLAlchemy
Home-page: https://github.com/maarten-dp/fast-alchemy
Author: Maarten De Paepe
Author-email: "maarten.de.paepe@gmail.com"
License: UNKNOWN
Platform: UNKNOWN
Classifier: Development Status :: 4 - Beta
Classifier: Operating System :: MacOS :: MacOS X
Classifier: Operating System :: Microsoft :: Windows
Classifier: Operating System :: POSIX
Classifier: License :: OSI Approved :: MIT License
Classifier: Programming Language :: Python
Classifier: Programming Language :: Python :: 3.6
License-File: LICENSE
Requires-Dist: Flask
Requires-Dist: Flask-SQLAlchemy
Requires-Dist: pyaml
